{
    "id": 5556,
    "publicAccess": true,
    "name": {
        "en": "Arts Council of Great Britain",
        "zh-hant": "Arts Council of Great Britain"
    },
    "alphaSortName": {
        "en": "Arts Council of Great Britain",
        "zh-hant": "Arts Council of Great Britain"
    },
    "type": "Organization",
    "roles": [
        "Publisher",
        "出版社"
    ],
    "displayBio": {
        "en": null,
        "zh-hant": null
    },
    "gender": {
        "en": "Not Applicable",
        "zh-hant": "不適用"
    },
    "beginDate": null,
    "endDate": null,
    "nationality": {
        "en": "British",
        "zh-hant": "英國籍"
    }
}