{
    "id": 1533,
    "publicAccess": true,
    "name": {
        "en": "Unknown (Western Asia)",
        "zh-hant": "佚名（西亞）"
    },
    "alphaSortName": {
        "en": "Unknown (Western Asia)",
        "zh-hant": "佚名（西亞）"
    },
    "type": "Individual",
    "roles": [
        "Designer",
        "設計師"
    ],
    "displayBio": {
        "en": null,
        "zh-hant": null
    },
    "gender": {
        "en": "Unknown",
        "zh-hant": "不詳"
    },
    "beginDate": null,
    "endDate": null,
    "nationality": {
        "en": null,
        "zh-hant": null
    }
}