{
    "objectID": 1907,
    "objectNumber": "2013.301",
    "sortNumber": 2013.301,
    "classification": {
        "area": {
            "rank": 1,
            "areacat": {
                "en": "Visual Art",
                "zh-hant": "視覺藝術"
            }
        },
        "category": {
            "rank": 2,
            "areacat": {
                "en": "Photography",
                "zh-hant": "攝影"
            }
        }
    },
    "consituents": [
        {
            "id": 520,
            "rank": 1,
            "roles": {
                "en": "Artist"
            },
            "names": {
                "en": "Yan Lei",
                "zh-hant": "顏磊"
            }
        }
    ],
    "title": {
        "en": "Invasion",
        "zh-hant": "入侵"
    },
    "displayDate": "1995",
    "beginDate": 1995,
    "endDate": 1995,
    "dimension": {
        "en": "sheet: 78 × 112 cm",
        "zh-hant": "紙本: 78 × 112 厘米"
    },
    "medium": {
        "en": "chromogenic colour print",
        "zh-hant": "彩色照片"
    },
    "creditLine": {
        "en": "M+, Hong Kong. Gift of Guan Yi, 2013",
        "zh-hant": "M+，香港，管藝捐贈，2013年"
    },
    "id": 1907
}