{
    "id": 3289,
    "sortNumber": "2012   767",
    "publicAccess": true,
    "objectNumber": "2012.767",
    "classification": {
        "area": {
            "en": "Visual Art",
            "zh-hant": "視覺藝術"
        },
        "category": {
            "en": "Sculpture",
            "zh-hant": "雕塑"
        },
        "archivalLevel": {
            "en": null,
            "zh-hant": null
        }
    },
    "title": {
        "en": "You never see a real square",
        "zh-hant": "你沒有看過正方形 !"
    },
    "displayDate": {
        "en": "2008",
        "zh-hant": "2008"
    },
    "beginDate": 2008,
    "endDate": 2008,
    "dimension": {
        "en": "frame: 21.5 × 30.5 × 3 cm",
        "zh-hant": "連框: 21.5 × 30.5 × 3 厘米"
    },
    "medium": {
        "en": "plastic ruler with frame",
        "zh-hant": "方框塑膠尺"
    },
    "creditLine": {
        "en": "M+ Sigg Collection, Hong Kong. By donation",
        "zh-hant": "M+ 希克藏品（捐贈），香港"
    },
    "constituents": [],
    "images": [
        {
            "altText": null
        }
    ],
    "color": {
        "predominant": [
            {
                "color": "#99938A",
                "value": 72.9
            },
            {
                "color": "#738239",
                "value": 15.2
            },
            {
                "color": "#7A7E88",
                "value": 6.7
            },
            {
                "color": "#383D25",
                "value": 1.1
            }
        ],
        "search": {
            "google": [
                {
                    "color": "green",
                    "value": 15.2
                },
                {
                    "color": "white",
                    "value": 51.5
                },
                {
                    "color": "gray",
                    "value": 79.6
                },
                {
                    "color": "brown",
                    "value": 1.1
                }
            ]
        }
    }
}