{
    "id": 9001,
    "sortNumber": "CA     29     2   24",
    "publicAccess": true,
    "objectNumber": "CA29/2/24",
    "classification": {
        "area": "Design and Architecture",
        "category": null,
        "archivalLevel": "Series"
    },
    "title": "Drawings and original documents, proposed condominium housing at Bushey Park, Singapore",
    "titleOther": "新加坡 Bushey Park擬建公寓大廈繪圖及原始文件",
    "displayDate": "[1969–circa 1982]",
    "displayDateOther": null,
    "beginDate": 1969,
    "endDate": 1984,
    "dimension": "54 items",
    "medium": null,
    "creditLine": "M+, Hong Kong. Gift of Architects Team 3, 2015",
    "constituents": null,
    "images": null,
    "color": {
        "predominant": null,
        "search": {
            "google": null
        }
    }
}