{
    "id": 9018,
    "sortNumber": "2018    49",
    "publicAccess": true,
    "objectNumber": "2018.49",
    "classification": {
        "area": {
            "en": [
                "Visual Art"
            ],
            "zh-hant": [
                "視覺藝術"
            ]
        },
        "category": {
            "en": [
                "Print"
            ],
            "zh-hant": [
                "版畫"
            ]
        },
        "archivalLevel": {
            "en": null,
            "zh-hant": null
        }
    },
    "title": {
        "en": "Floor Event (invitation)",
        "zh-hant": "樓層活動（邀請函）"
    },
    "displayDate": {
        "en": "1971",
        "zh-hant": "1971"
    },
    "beginDate": 1971,
    "endDate": 1971,
    "dimension": {
        "en": "sheet: 10 × 14.9 cm",
        "zh-hant": "整體: 10 × 14.8 厘米"
    },
    "medium": {
        "en": "silkscreen and offset print",
        "zh-hant": "絲網印刷、柯式印刷"
    },
    "creditLine": {
        "en": "M+, Hong Kong. Gift of Hikosaka Naoyoshi, 2017",
        "zh-hant": "M+，香港，Hikosaka Naoyoshi捐贈，2017年"
    },
    "constituents": [],
    "images": [
        {
            "altText": null
        }
    ],
    "color": {
        "predominant": [
            {
                "color": "#D1D1D5",
                "value": 35.3
            },
            {
                "color": "#85141D",
                "value": 13.2
            },
            {
                "color": "#3E3C3F",
                "value": 11.1
            },
            {
                "color": "#D6DADB",
                "value": 7.4
            },
            {
                "color": "#73706F",
                "value": 5.3
            },
            {
                "color": "#464443",
                "value": 5.2
            },
            {
                "color": "#7E7D81",
                "value": 5
            },
            {
                "color": "#702B2E",
                "value": 2.8
            },
            {
                "color": "#808384",
                "value": 1.8
            },
            {
                "color": "#521812",
                "value": 1.7
            },
            {
                "color": "#767375",
                "value": 1.7
            },
            {
                "color": "#7A7B77",
                "value": 1.6
            },
            {
                "color": "#4E1F1C",
                "value": 1.5
            },
            {
                "color": "#C5B7BB",
                "value": 1.1
            },
            {
                "color": "#7F817F",
                "value": 1
            }
        ],
        "search": {
            "google": [
                {
                    "color": "red",
                    "value": 19.3
                },
                {
                    "color": "gray",
                    "value": 17.6
                },
                {
                    "color": "white",
                    "value": 42.7
                },
                {
                    "color": "black",
                    "value": 16.4
                }
            ]
        }
    },
    "dimensionDetails": {
        "element": "sheet",
        "unit": "cm",
        "width": 14.9,
        "height": 10,
        "depth": null
    }
}