{
    "id": 9157,
    "sortNumber": "CA      9     2    3",
    "publicAccess": true,
    "objectNumber": "CA9/2/3",
    "classification": {
        "area": {
            "en": "Design and Architecture",
            "zh-hant": "設計與建築"
        },
        "category": {
            "en": "Architectural Drawing",
            "zh-hant": "建築圖"
        },
        "archivalLevel": {
            "en": "Item",
            "zh-hant": "單件"
        }
    },
    "title": {
        "en": "Level four floor plan (podium plan), Shatin Centre (1977–1981), Hong Kong",
        "zh-hant": "香港沙田中心（1977至1981年）四樓平台平面圖"
    },
    "displayDate": {
        "en": "14 March 1978, revised 1978–1984",
        "zh-hant": "14 March 1978, revised 1978–1984"
    },
    "beginDate": 1978,
    "endDate": 1984,
    "dimension": {
        "en": "sheet: 75.5 x 109 cm",
        "zh-hant": "sheet: 75.5 x 109 cm"
    },
    "medium": {
        "en": "carbon and graphite on transparent paper",
        "zh-hant": "carbon and graphite on transparent paper"
    },
    "creditLine": {
        "en": "M+, Hong Kong. Gift of Andrew Lee King Fun & Associates Architects Limited, 2013",
        "zh-hant": "M+，香港，李景勳、雷煥庭建築師事務所捐贈，2013年"
    },
    "constituents": [],
    "images": [
        {
            "altText": null
        }
    ],
    "color": {
        "predominant": [
            {
                "color": "#CAB48C",
                "value": 72.9
            },
            {
                "color": "#D4CAB3",
                "value": 16.1
            },
            {
                "color": "#988669",
                "value": 5
            },
            {
                "color": "#DCDCD5",
                "value": 2.5
            }
        ],
        "search": {
            "google": [
                {
                    "color": "gray",
                    "value": 81.2
                },
                {
                    "color": "brown",
                    "value": 5
                },
                {
                    "color": "orange",
                    "value": 89
                },
                {
                    "color": "white",
                    "value": 2.5
                }
            ]
        }
    },
    "dimensionDetails": {
        "element": "sheet",
        "unit": "cm",
        "width": 109,
        "height": 75.5,
        "depth": null
    }
}