{
    "id": 9257,
    "sortNumber": "CA     29     2   15",
    "publicAccess": true,
    "objectNumber": "CA29/2/15",
    "classification": {
        "area": "Design and Architecture",
        "category": "Archival Documentation",
        "archivalLevel": "Item"
    },
    "title": "Brief, Singapore Telephone Board Communications Centre project, Singapore",
    "titleOther": "新加坡電話局通訊中心項目簡介",
    "displayDate": "July 1973",
    "displayDateOther": null,
    "beginDate": 1973,
    "endDate": 1973,
    "dimension": "overall: 29.7 x 21 cm\r\n33 pages",
    "medium": "photocopy on paper",
    "creditLine": "M+, Hong Kong. Gift of Architects Team 3, 2015",
    "constituents": null,
    "images": null,
    "color": {
        "predominant": null,
        "search": {
            "google": null
        }
    }
}