{
    "objectID": 9804,
    "objectNumber": "2018.15",
    "sortNumber": 2018.15,
    "classification": {
        "area": {
            "rank": 1,
            "areacat": {
                "en": "Design and Architecture",
                "zh-hant": "設計與建築"
            }
        },
        "category": {
            "rank": 2,
            "areacat": {
                "en": "Furniture",
                "zh-hant": "家具"
            }
        }
    },
    "consituents": [
        {
            "id": 858,
            "rank": 1,
            "roles": {
                "en": "Designer"
            },
            "names": {
                "en": "Hans Tan",
                "zh-hant": "陳彥翰"
            }
        },
        {
            "id": 858,
            "rank": 1,
            "roles": {
                "en": "Seller"
            },
            "names": {
                "en": "Hans Tan",
                "zh-hant": "陳彥翰"
            }
        },
        {
            "id": 858,
            "rank": 1,
            "roles": {
                "en": "Former Owner"
            },
            "names": {
                "en": "Hans Tan",
                "zh-hant": "陳彥翰"
            }
        }
    ],
    "title": {
        "en": "Pour",
        "zh-hant": "倒"
    },
    "displayDate": "2015",
    "beginDate": 2015,
    "endDate": 2015,
    "dimension": {
        "en": "overall: 53 × 50 × 50 cm",
        "zh-hant": "整體: 53 × 50 × 50 厘米"
    },
    "medium": {
        "en": "epoxy resin and powder-coated steel",
        "zh-hant": "人工樹脂及粉末塗層鋼"
    },
    "creditLine": {
        "en": "M+, Hong Kong",
        "zh-hant": "M+，香港"
    },
    "id": 9804
}