{
    "id": 851,
    "publicAccess": true,
    "name": {
        "en": "Aisha Khalid",
        "zh-hant": "Aisha Khalid"
    },
    "alphaSortName": {
        "en": "Khalid, Aisha",
        "zh-hant": "Khalid, Aisha"
    },
    "type": "Individual",
    "roles": [
        "Artist"
    ],
    "displayBio": {
        "en": "Pakistani, born 1972",
        "zh-hant": "巴基斯坦籍，生於1972年"
    },
    "gender": {
        "en": "Female",
        "zh-hant": "女性"
    },
    "beginDate": 1972,
    "endDate": null,
    "nationality": {
        "en": "Pakistani",
        "zh-hant": "巴基斯坦籍"
    }
}