{
    "constituentID": 164,
    "name": {
        "en": {
            "id": "156",
            "alphasort": "Diao, David",
            "displayname": "David Diao"
        },
        "zh-hant": {
            "id": "1231",
            "alphasort": "刁, 德謙",
            "displayname": "刁德謙"
        }
    },
    "type": "Individual",
    "gender": {
        "en": "Male",
        "zh-hant": "男性"
    },
    "displayBio": {},
    "nationality": "American",
    "beginDate": 1943,
    "deathyear": null,
    "id": 164
}