{
    "constituentID": 192,
    "name": {
        "en": {
            "displayName": "Gu Wenda",
            "alphasort": "Gu, Wenda"
        },
        "zh-hant": {
            "displayName": "谷文達",
            "alphasort": "谷, 文達"
        }
    },
    "type": "Individual",
    "gender": {
        "en": "Male",
        "zh-hant": "男性"
    },
    "displayBio": {
        "en": "Chinese, born 1955",
        "zh-hant": "中國籍，生於1955年"
    },
    "nationality": {
        "en": "Chinese",
        "zh-hant": "中國籍"
    },
    "region": {
        "en": "Mainland China",
        "zh-hant": "中國內地"
    },
    "activeCity": {
        "en": "New York City"
    },
    "birthCity": {
        "en": "Shanghai"
    },
    "deathCity": null,
    "beginDate": 1955,
    "endDate": null,
    "exhibitions": {
        "biographies": null,
        "purpose": null
    },
    "id": 192
}