{
    "constituentID": 252,
    "name": {
        "en": {
            "displayName": "Kuramata Shiro",
            "alphasort": "Kuramata, Shiro"
        },
        "zh-hant": {
            "displayName": "倉俁史朗",
            "alphasort": "倉俁史朗"
        }
    },
    "type": "Individual",
    "gender": {
        "en": "Male",
        "zh-hant": "男性"
    },
    "displayBio": {
        "en": "Japanese, 1934–1991",
        "zh-hant": "日本籍，1934–1991年"
    },
    "nationality": {
        "en": "Japanese",
        "zh-hant": "日本籍"
    },
    "region": {
        "en": "East Asia",
        "zh-hant": "東亞"
    },
    "activeCity": null,
    "birthCity": {
        "en": "Tokyo"
    },
    "deathCity": null,
    "beginDate": 1934,
    "endDate": 1991,
    "exhibitions": {
        "biographies": null,
        "purpose": null
    },
    "id": 252
}