{
    "constituentID": 315,
    "name": {
        "en": {
            "displayName": "Liu Zheng",
            "alphasort": "Liu, Zheng"
        },
        "zh-hant": {
            "displayName": "劉崢",
            "alphasort": "劉, 崢"
        }
    },
    "type": "Individual",
    "gender": {
        "en": "Male",
        "zh-hant": "男性"
    },
    "displayBio": {
        "en": "Chinese, born 1969",
        "zh-hant": "中國籍，生於1969年"
    },
    "nationality": {
        "en": "Chinese",
        "zh-hant": "中國籍"
    },
    "region": {
        "en": "Mainland China",
        "zh-hant": "中國內地"
    },
    "activeCity": {
        "en": "Beijing",
        "zh-hant": "北京"
    },
    "birthCity": {
        "en": "Wuqiang"
    },
    "deathCity": null,
    "beginDate": 1969,
    "endDate": null,
    "exhibitions": {
        "biographies": null,
        "purpose": null
    },
    "id": 315
}