{
    "constituentID": 479,
    "name": {
        "en": {
            "displayName": "Frank Lloyd Wright",
            "alphasort": "Wright, Frank Lloyd"
        },
        "zh-hant": {
            "displayName": "弗蘭克·勞埃德·賴特",
            "alphasort": "弗蘭克·勞埃德·賴特"
        }
    },
    "type": "Individual",
    "gender": {
        "en": "Male",
        "zh-hant": "男性"
    },
    "displayBio": {
        "en": "American, 1867–1959",
        "zh-hant": "美國籍，1867–1959年"
    },
    "nationality": {
        "en": "American",
        "zh-hant": "美國籍"
    },
    "region": {
        "en": "Americas",
        "zh-hant": "美洲"
    },
    "activeCity": null,
    "birthCity": {
        "en": "Richland Center"
    },
    "deathCity": null,
    "beginDate": 1867,
    "endDate": 1959,
    "exhibitions": {
        "biographies": null,
        "purpose": null
    },
    "id": 479
}