{
    "constituentID": 54,
    "name": {
        "en": {
            "id": "46",
            "alphasort": "Palmer & Turner (P&T Group)",
            "displayname": "Palmer & Turner (P&T Group)"
        },
        "zh-hant": {
            "id": "1170",
            "alphasort": "巴馬丹拿集團",
            "displayname": "巴馬丹拿集團"
        }
    },
    "type": "Organization",
    "gender": {
        "zh-hant": null
    },
    "displayBio": {},
    "nationality": "Hong Kong",
    "beginDate": 1868,
    "deathyear": null,
    "id": 54
}