{
    "objectID": 768,
    "objectNumber": "2012.1515",
    "sortNumber": 2012.1515,
    "classification": {
        "area": {
            "rank": 1,
            "areacat": {
                "en": "Visual Art",
                "zh-hant": "視覺藝術"
            }
        },
        "category": {
            "rank": 2,
            "areacat": {
                "en": "Installation",
                "zh-hant": "裝置藝術"
            }
        }
    },
    "consituents": [
        {
            "id": 44,
            "rank": 1,
            "roles": {
                "en": "Artist"
            },
            "names": {
                "en": "Tsang Tsou-choi (a.k.a. King of Kowloon)",
                "zh-hant": "曾灶財"
            }
        }
    ],
    "title": {
        "en": "Untitled (pair of wooden doors)",
        "zh-hant": "無題 (門)"
    },
    "displayDate": "2003",
    "beginDate": 2003,
    "endDate": 2003,
    "dimension": {
        "en": "overall (each (approx.)): 211.5 × 167.5 × 11.8 cm",
        "zh-hant": "各: 170 × 220 × 6 厘米",
        "zh-hans": "各: 170 × 220 × 6 厘米"
    },
    "medium": {
        "en": "industrial paint, acrylic, wood",
        "zh-hant": "工業用漆、塑膠彩、木",
        "zh-hans": "水墨及塑胶彩板本"
    },
    "creditLine": {
        "en": "M+, Hong Kong. Museum purchase and gift of Timon Wehrli, Red Dog Studios, 2012",
        "zh-hant": "M+，香港，由Red Dog Studios的Tim Wehrli捐贈以協助博物館購買，2012年",
        "zh-hans": "香港M+，由Red Dog Studios的Tim Wehrli捐赠以协助博物馆购买，2012年"
    },
    "id": 768
}