{
    "id": 5624,
    "sortNumber": "2016    11",
    "publicAccess": true,
    "objectNumber": "2016.11",
    "classification": {
        "area": {
            "en": "Visual Art",
            "zh-hant": "視覺藝術"
        },
        "category": {
            "en": "Sculpture",
            "zh-hant": "雕塑"
        },
        "archivalLevel": {
            "en": null,
            "zh-hant": null
        }
    },
    "title": {
        "en": "Untitled (Cords)",
        "zh-hant": "無題（繩子）"
    },
    "displayDate": {
        "en": "1957",
        "zh-hant": "1957"
    },
    "beginDate": 1957,
    "endDate": 1957,
    "dimension": {
        "en": "65 × 91 cm",
        "zh-hant": "65 × 91 厘米"
    },
    "medium": {
        "en": "coloured cord and acrylic on canvas",
        "zh-hant": "有色繩索、塑膠彩布本"
    },
    "creditLine": {
        "en": "M+, Hong Kong",
        "zh-hant": "M+，香港"
    },
    "constituents": [],
    "images": [
        {
            "altText": null
        }
    ],
    "color": {
        "predominant": [
            {
                "color": "#242927",
                "value": 41.6
            },
            {
                "color": "#2A2926",
                "value": 17
            },
            {
                "color": "#DED7CD",
                "value": 6.6
            },
            {
                "color": "#232224",
                "value": 6.5
            },
            {
                "color": "#172220",
                "value": 3.7
            },
            {
                "color": "#161E20",
                "value": 3.5
            },
            {
                "color": "#EBEBE1",
                "value": 2.8
            },
            {
                "color": "#2B251A",
                "value": 1.5
            },
            {
                "color": "#32221D",
                "value": 1.5
            },
            {
                "color": "#D9C491",
                "value": 1.4
            },
            {
                "color": "#870E14",
                "value": 1.2
            },
            {
                "color": "#CF8966",
                "value": 1.1
            },
            {
                "color": "#EDEFED",
                "value": 0.9
            },
            {
                "color": "#805742",
                "value": 0.9
            },
            {
                "color": "#C3222A",
                "value": 0.8
            },
            {
                "color": "#EFEDEF",
                "value": 0.8
            },
            {
                "color": "#817050",
                "value": 0.7
            },
            {
                "color": "#887970",
                "value": 0.7
            },
            {
                "color": "#01020E",
                "value": 0.7
            },
            {
                "color": "#2B0506",
                "value": 0.6
            },
            {
                "color": "#D9AE18",
                "value": 0.6
            }
        ],
        "search": {
            "google": [
                {
                    "color": "orange",
                    "value": 3.2
                },
                {
                    "color": "red",
                    "value": 2.6
                },
                {
                    "color": "gray",
                    "value": 0.7
                },
                {
                    "color": "white",
                    "value": 11.1
                },
                {
                    "color": "black",
                    "value": 76
                },
                {
                    "color": "yellow",
                    "value": 0.8
                },
                {
                    "color": "brown",
                    "value": 1.6
                }
            ]
        }
    },
    "dimensionDetails": {
        "element": "overall",
        "unit": "cm",
        "width": 91,
        "height": 65,
        "depth": null
    }
}