{
    "id": 6594,
    "publicAccess": true,
    "name": {
        "en": "Taiwan Amoeba Design Association",
        "zh-hant": "台灣設計協會"
    },
    "alphaSortName": {
        "en": "Taiwan Amoeba Design Association",
        "zh-hant": "台灣設計協會"
    },
    "type": "Organization",
    "roles": [
        "Publisher",
        "出版社"
    ],
    "displayBio": {
        "en": "established Taiwan, 1971",
        "zh-hant": "established Taiwan, 1971"
    },
    "gender": {
        "en": "Not Applicable",
        "zh-hant": "不適用"
    },
    "beginDate": 1971,
    "endDate": null,
    "nationality": {
        "en": "Taiwanese",
        "zh-hant": "台灣籍"
    }
}