{
    "objectID": 4037,
    "objectNumber": "2015.353",
    "sortNumber": 2015.353,
    "classification": {
        "area": {
            "rank": 1,
            "areacat": {
                "en": "Design and Architecture",
                "zh-hant": "設計與建築"
            }
        },
        "category": {
            "rank": 2,
            "areacat": {
                "en": "Book/Periodical",
                "zh-hant": "書藉/期刊"
            }
        }
    },
    "consituents": [
        {
            "id": 846,
            "rank": 1,
            "roles": {
                "en": "Design Firm"
            },
            "names": {
                "en": "WORK PTE LTD"
            }
        },
        {
            "id": 846,
            "rank": 1,
            "roles": {
                "en": "Seller"
            },
            "names": {
                "en": "WORK PTE LTD"
            }
        },
        {
            "id": 1302,
            "rank": 2,
            "roles": {
                "en": "Designer"
            },
            "names": {
                "en": "Theseus Chan",
                "zh-hant": "陳益"
            }
        },
        {
            "id": 3033,
            "rank": 3,
            "roles": {
                "en": "Design Firm"
            },
            "names": {
                "en": "Comme des Garçons"
            }
        }
    ],
    "title": {
        "en": "WERK No. 12/GUERRILLAZINE No.3: The Outsiders (In Collaboration With Comme Des Garçons Guerrilla Stores)",
        "zh-hant": "WERK第12期 ／ GUERRILLAZINE第3期：圈外人"
    },
    "displayDate": "2005",
    "beginDate": 2005,
    "endDate": 2005,
    "dimension": {
        "en": "overall (closed): 2 × 22.8 × 31.9 cm",
        "zh-hant": "整體 (合上): 2 × 22.8 × 31.9 厘米"
    },
    "medium": {
        "en": "offset print on paper",
        "zh-hant": "柯式印刷紙本"
    },
    "creditLine": {
        "en": "M+, Hong Kong",
        "zh-hant": "M+，香港"
    },
    "id": 4037
}