{
    "objectID": 4924,
    "objectNumber": "2016.389",
    "sortNumber": 2016.389,
    "classification": {
        "area": {
            "rank": 1,
            "areacat": {
                "en": "Visual Art",
                "zh-hant": "視覺藝術"
            }
        },
        "category": {
            "rank": 2,
            "areacat": {
                "en": "Collage",
                "zh-hant": "拼貼"
            }
        }
    },
    "consituents": [
        {
            "id": 1031,
            "rank": 1,
            "roles": {
                "en": "Artist"
            },
            "names": {
                "en": "Tanaami Keiichi"
            }
        }
    ],
    "title": {
        "en": "Untitled (Collagebook4_02)",
        "zh-hant": "無題（拼貼簿4_02）",
        "zh-hans": "无题（拼贴簿4_02）"
    },
    "displayDate": "1969",
    "beginDate": 1969,
    "endDate": 1969,
    "dimension": {
        "en": "sheet: 25.5 × 33.8 cm",
        "zh-hant": "紙本: 25.5 × 33.8 厘米"
    },
    "medium": {
        "en": "ink, marker, collage on paper",
        "zh-hant": "墨水、箱頭筆、拼貼紙本",
        "zh-hans": "水墨丶箱头笔及拼贴纸本"
    },
    "creditLine": {
        "en": "M+, Hong Kong",
        "zh-hant": "M+，香港",
        "zh-hans": "香港M+"
    },
    "id": 4924
}