{
    "id": 14118,
    "sortNumber": "CA     39     2   30",
    "publicAccess": true,
    "objectNumber": "CA39/2/30",
    "classification": {
        "area": {
            "en": "Design and Architecture",
            "zh-hant": "設計與建築"
        },
        "category": {
            "en": "Archival Documentation",
            "zh-hant": "檔存文件"
        },
        "archivalLevel": {
            "en": "File",
            "zh-hant": "案卷"
        }
    },
    "title": {
        "en": "美國紐約大頸猶太教堂（1961至1967年）項目文件",
        "zh-hant": "Project file, Great Neck Synagogue (1961–1967), Great Neck, New York, USA"
    },
    "displayDate": {
        "en": "[circa 1963]",
        "zh-hant": null
    },
    "beginDate": 1961,
    "endDate": 1967,
    "dimension": {
        "en": "3 items",
        "zh-hant": "3 items"
    },
    "medium": {
        "en": "printout on paper; photocopy on paper, mimeograph copy on paper",
        "zh-hant": "printout on paper; photocopy on paper, mimeograph copy on paper"
    },
    "creditLine": {
        "en": "M+, Hong Kong. Gift of Chiu-Hwa Wang, 2017",
        "zh-hant": "M+, Hong Kong. Gift of Chiu-Hwa Wang, 2017"
    },
    "constituents": [],
    "images": [
        {
            "altText": null
        }
    ],
    "color": {
        "predominant": [
            {
                "color": "#FCFCFC",
                "value": 95.9
            }
        ],
        "search": {
            "google": [
                {
                    "color": "white",
                    "value": 95.9
                }
            ]
        }
    }
}