{
    "id": 14542,
    "sortNumber": "CA     30     2   19",
    "publicAccess": true,
    "objectNumber": "CA30/2/19",
    "classification": {
        "area": "Design and Architecture",
        "category": null,
        "archivalLevel": "Series"
    },
    "title": "Photographic material, Asia Cement Building (circa 1966), Taipei, Taiwan",
    "titleOther": "台灣台北市亞洲水泥大樓（約1966年）影像資料",
    "displayDate": "[circa 1966]",
    "displayDateOther": null,
    "beginDate": 1964,
    "endDate": 1968,
    "dimension": "2 items",
    "medium": null,
    "creditLine": "M+, Hong Kong. Gift of Family of Wang Dahong, 2015",
    "constituents": null,
    "images": null,
    "color": {
        "predominant": null,
        "search": {
            "google": null
        }
    }
}