{
    "id": 14737,
    "sortNumber": "CA     30     5    1    48",
    "publicAccess": true,
    "objectNumber": "CA30/5/1/48",
    "classification": {
        "area": "Design and Architecture",
        "category": "Archival Documentation",
        "archivalLevel": "Item"
    },
    "title": "Draft introduction, '\"Phantasmagoria\", memoirs of a child's former life, written on board the spaceyacht Medusa, in the year of our Lord 2069'",
    "titleOther": "小說《幻城》序言草稿",
    "displayDate": "May 1990",
    "displayDateOther": null,
    "beginDate": 1990,
    "endDate": 1990,
    "dimension": "sheet: 27.4 x 21.1 cm",
    "medium": "typewriter ink on paper, ink on paper",
    "creditLine": "M+, Hong Kong. Gift of Family of Wang Dahong, 2016",
    "constituents": null,
    "images": [],
    "color": {
        "predominant": [
            {
                "color": "#DAD3C7",
                "value": 64.1
            },
            {
                "color": "#E0E0D7",
                "value": 28.5
            },
            {
                "color": "#8A8A82",
                "value": 2.5
            }
        ],
        "search": {
            "google": [
                {
                    "color": "gray",
                    "value": 2.5
                },
                {
                    "color": "white",
                    "value": 92.6
                }
            ]
        }
    }
}