{
    "objectID": 2767,
    "objectNumber": "2012.804",
    "sortNumber": 2012.804,
    "classification": {
        "area": {
            "rank": 1,
            "areacat": {
                "en": "Visual Art",
                "zh-hant": "視覺藝術"
            }
        },
        "category": {
            "rank": 2,
            "areacat": {
                "en": "Painting",
                "zh-hant": "繪畫"
            }
        }
    },
    "consituents": [
        {
            "id": 374,
            "rank": 1,
            "roles": {
                "en": "Artist"
            },
            "names": {
                "en": "Qin Qi",
                "zh-hant": "秦琦"
            }
        }
    ],
    "title": {
        "en": "Hello",
        "zh-hant": "你好"
    },
    "displayDate": "circa 2004",
    "beginDate": 2004,
    "endDate": 2004,
    "dimension": {
        "en": "overall: 100 × 75.6 × 2.3 cm",
        "zh-hant": "整體: 100 × 75.6 × 2.3 厘米"
    },
    "medium": {
        "en": "oil on canvas",
        "zh-hant": "油彩布本"
    },
    "creditLine": {
        "en": "M+ Sigg Collection, Hong Kong. By donation",
        "zh-hant": "M+ 希克藏品（捐贈），香港"
    },
    "id": 2767
}