{
    "id": 4055,
    "publicAccess": true,
    "name": {
        "en": "Hu Boxiang",
        "zh-hant": "胡伯翔"
    },
    "alphaSortName": {
        "en": "Boxiang, Hu",
        "zh-hant": "胡, 伯翔"
    },
    "type": "Individual",
    "roles": [
        "Artist",
        "藝術家"
    ],
    "displayBio": {
        "en": "Chinese, 1896 – 1989",
        "zh-hant": "中國籍，1896–1989年"
    },
    "gender": {
        "en": "Male",
        "zh-hant": "男性"
    },
    "beginDate": 1896,
    "endDate": 1989,
    "nationality": {
        "en": "Chinese",
        "zh-hant": "中國籍"
    }
}