{
    "id": 4103,
    "publicAccess": true,
    "name": {
        "en": "Great Wall Photographers",
        "zh-hant": "長城影業彩色中心"
    },
    "alphaSortName": {
        "en": "Great Wall Photographers",
        "zh-hant": "長城影業彩色中心"
    },
    "type": "Organization",
    "roles": [
        "Publisher",
        "出版社"
    ],
    "displayBio": {
        "en": "Malaysian, established mid 20th century",
        "zh-hant": "Malaysian, established mid 20th century"
    },
    "gender": {
        "en": "Not Applicable",
        "zh-hant": "不適用"
    },
    "beginDate": 1950,
    "endDate": null,
    "nationality": {
        "en": "Malaysian",
        "zh-hant": "馬來西亞籍"
    }
}