{
    "id": 11867,
    "sortNumber": "CA     21     2    2",
    "publicAccess": true,
    "objectNumber": "CA21/2/2",
    "classification": {
        "area": "Design and Architecture",
        "category": "Architectural Drawing",
        "archivalLevel": "Item"
    },
    "title": "Sketches, planters and vegetation, Yokohama Floating Parking, Yokohama, Japan",
    "titleOther": "日本橫濱水上停車場花槽及植物草圖",
    "displayDate": "[circa 1991]",
    "displayDateOther": null,
    "beginDate": 1989,
    "endDate": 1991,
    "dimension": "sheet: 33.7 x 21.6 cm",
    "medium": "ink and graphite on paper",
    "creditLine": "M+, Hong Kong. Gift of Gaetano Pesce, 2014",
    "constituents": null,
    "images": null,
    "color": {
        "predominant": null,
        "search": {
            "google": null
        }
    }
}